mapper/__init__.py
mapper/core/__init__.py
mapper/core/mapper.py
mapper/core/singleton.py
py_object_mapper-0.1.0.dist-info/METADATA
py_object_mapper-0.1.0.dist-info/WHEEL
util/__init__.py
util/catch.py
py_object_mapper-0.1.0.dist-info/RECORD
